
{
"noun":[  
        "gesture",
        "texture",
        "deployment",
        "dialectic",
        "value",
        "body",
        "material",
        "discourse",
        "legibility",
        "abstraction",
        "desire",
        "fantasy",
        "identity",
        "assimilation",
        "pleasure",
        "reading",
        "assessment",
        "archive",
        "potential",
        "resistance",
        "enforcement",
        "recognition",
        "solidarity",
        "refusal",
        "performance",
        "reproduction",
        "ideology",
        "affect",
        "disidentification",
        "identification",
        "personhood",
        "hegemony",
        "silence",
        "evidence",
        "ambivalence",
        "form",
        "sex",
        "gender",
        "critique",
        "intimacy",
        "sensibility",
        "indexicality",
        "ephemerality",
        "technology",
        "signifier",
        "here-and-now",
        "imagination",
        "simulacrum",
        "subjectivity",
        "interpellation"
    ],    
    "plural_noun":[  
        "politics",
        "aesthetics",
        "bodies",
        "tactics",
        "archives",
        "diagnostics",
        "erotics",
        "intimacies",
        "realities",
        "subjectivities"
    ],    
    "proper_noun":[  
        "David Getsy",
        "Jennifer Doyle",
        "Jeanne Vaccaro",
        "Butler",
        "Munoz",
        "Berlant",
        "Ann Cvetkovich",
        "Zoe Leonard",
        "Tim Dean",
        "Sontag",
        "Samuel Delany",
        "Warner",
        "Foucault",
        "Lacan",
        "Bersani",
        "Edelman",
        "Halperin",
        "Halberstam",
        "Sedgwick",
        "trans studies",
        "queer theory",
        "critical theory",
        "feminism",
        "post-structuralism"
    ],
    "transitive_verb":[  
        "generate",
        "deploy",
        "subordinate",
        "theorize",
        "accumulate",
        "marginalize",
        "displace",
        "invoke",
        "access",
        "inhabit",
        "establish",
        "archive",
        "critique",
        "obscure",
        "produce",
        "push",
        "propose",
        "represent",
        "express",
        "interrogate",
        "challenge",
        "address",
        "forge",
        "seek",
        "deconstruct",
        "incorporate",
        "delineate",
        "perform",
        "animate",
        "interpellate"
    ],
    "intransitive_verb":[  
        "gesture",
        "operate",
        "emerge",
        "occur",
        "play",
        "resonate",
        "figure",
        "linger",
        "perform",
        "theorize",
        "accumulate"
    ],
    "preposition":[  
        "within",
        "within a space of",
        "among",
        "toward",
        "toward a space of",
        "as",
        "as a site of",
        "as a space of",
        "across",
        "with and across",
        "with and against",
        "against",
        "against the grain of",
        "beyond",
        "inside",
        "outside"
    ],    
    "adjective":[  
        "generative",
        "transgender",
        "nongeometrical",
        "haptic",
        "affective",
        "diagnostic",
        "administrative",
        "quotidian",
        "conceptual",
        "utilitarian",
        "historical",
        "feminine",
        "material",
        "marginalized",
        "discursive",
        "performative",
        "sexual",
        "gendered",
        "aesthetic",
        "iconographic",
        "taxonomical",
        "queer",
        "abject",
        "proprioceptive",
        "past",
        "formal",
        "tactical",
        "archival",
        "mutual",
        "hyperbolic",
        "similar",
        "erotic",
        "feminist",
        "sexualized",
        "ambivalent",
        "ephemeral",
        "institutional",
        "innate",
        "sexed",
        "withheld",
        "embodied",
        "minoritarian",
        "hegemonic",
        "dominant",
        "world-making",
        "world-building",
        "utopian",
        "assimilationist",
        "always-already",
        "critical"
    ],
    "adverb":[  
        "queerly",
        "obsessively",
        "intrinsically",
        "prominently"
    ],     
    "adjective_noun":[  
        "#noun#",
        "the #adjective#",
        "#adjective# #noun#",
        "#adjective.a# #noun#",
        "#noun# of #noun#",
        "#noun.a# of #noun#",
        "#noun# of #plural_noun#",
        "#noun.a# of #plural_noun#"
    ],

    "noun_phrase":[  
        "a kind of '#adjective# #noun#'",
        "a sort of '#noun# of #noun#'",
        "freedom from #adjective_noun#",
        "freedom from #noun#",
        "the #noun# as #noun#",
        "questions of #noun#",
        "questions of #plural_noun#",
        "the category '#noun#'",
        "the category '#plural_noun#'",
        "the concept of #adjective_noun#",
        "the #thing# as #thing#",
        "#thing.a# that is not-#thing#",
        "that which is #transitive_verb.ed#"
    ],    
    "object":[  
        "#noun#",
        "#noun.a#",
        "#plural_noun#",
        "#adjective_noun#",
        "#noun_phrase#",
        "the #adjective#"
    ],    
    "singular_predicate":[  
	"#transitive_verb.es# #object#", 
	"#transitive_verb.es# #object# #preposition# #object#",        
	"#intransitive_verb.es# #preposition# #object#"
    ],
    "plural_predicate":[  
        "#transitive_verb# #object#",
        "#transitive_verb# #object# #preposition# #object#",
        "#intransitive_verb# #preposition# #object#"
    ],    
    "addendum":[  
        ", moving between #noun# and #noun#",
        " (that is, the #adjective#)",
        " (which is not to say that #phrase#)",
        " (by the same token, #phrase#)",
        "; it #singular_predicate#, it #singular_predicate#",
        " (#adjective#, #adjective#)"
    ],    
    "phrase":[  
        "#subject# #singular_predicate#",
        "#subject# #singular_predicate#",
        "#subject# #singular_predicate#",
        "#subject# #singular_predicate#",
        "#subject# is #adjective#",
        "#subject# is #adjective#, #adjective#, #adjective#",
        "#subject# is, as we know, #adjective#",
        "#subject# becomes #noun_phrase#",
        "to #plural_predicate# is to #plural_predicate#"
    ],
   
    "sentence":[  
        "#phrase#.",
        "#phrase#.",
        "#phrase#.",
        "#phrase#.",
        "#phrase##addendum#.",
        "#phrase##addendum#.",
        "it is not that #phrase#; rather, that #phrase#.",
        "it is #subject# that #singular_predicate#."
        "in #adjective_noun#, #phrase#."
    ],    
    "subsidiary_sentence":[  
        "indeed, #sentence#",
        "with regard to #subject#, #sentence#",
        "the question then becomes, #question#",
        "nevertheless, #sentence#",
        "instead, #sentence#",
        "an example: #sentence#",
        "for instance, #sentence#",
        "hence, #sentence#",
        "however, #sentence#",
        "and yet, #sentence#",
        "it #intransitive_verb.es#; it #intransitive_verb.es#.",        
        "this is what #proper_noun# calls '#adjective_noun#'.",
        "take #proper_noun#'s idea of #noun_phrase#.",
        "from #proper_noun#'s perspective, #sentence#",
        "as #proper_noun# notes, #sentence#",
        "#proper_noun# makes the claim that #sentence#"
    ],
    "question":[  
        "how is it that #phrase#?",
        "how might we #plural_predicate#?",
        "if we are to #plural_predicate#, what might then #plural_predicate#?",
        "what becomes of #subject#, if #phrase#?",
        "which is more #adjective#: #object#, or #object#?",
        "what to make of #subject#?",
        "what is '#adjective_noun#'?",
        "what #noun# #singular_predicate#?"
    ],
    "subsidiary_question":[  
        "indeed, #question#",
        "and #question#",
        "that is, #question#"
    ],     
 
   
    "tweet":[  
	"#sentence.capitalize#",
        "#sentence.capitalize# #sentence.capitalize#",
        "#sentence.capitalize# #subsidiary_sentence.capitalize#",
        "#sentence.capitalize# #question.capitalize#",
        "#sentence.capitalize# #subsidiary_sentence.capitalize# #question.capitalize#",        
        "#question.capitalize#",
        "#question.capitalize# #subsidiary_question.capitalize#",
        "#question.capitalize# #subsidiary_sentence.capitalize#"
    ],
    "origin":[  
        "#[thing:#noun#][subject:#adjective_noun#][plural_subject:#plural_noun_subj#]tweet#"
    ]
}
